robyn/__init__.py
robyn/robyn.py
robyn/_deprecate/ridge_model_builder_e2e_wrong_scaling.py
robyn/_deprecate/ridge_model_builder_preallocator_fix.py
robyn/_deprecate/ridge_model_builder_preallocator_fix_nov26.py
robyn/_deprecate/allocator_dec1_good_v1/constants.py
robyn/_deprecate/allocator_dec1_good_v1/data_preparation.py
robyn/_deprecate/allocator_dec1_good_v1/optimizer.py
robyn/_deprecate/allocator_dec1_good_v1/utils.py
robyn/_deprecate/allocator_dec1_good_v1/entities/allocation_params.py
robyn/_deprecate/allocator_dec1_good_v1/entities/allocation_result.py
robyn/_deprecate/allocator_dec1_good_v1/entities/constraints.py
robyn/_deprecate/allocator_dec1_good_v1/entities/optimization_result.py
robyn/_deprecate/ridge/ridge_data_builder.py
robyn/_deprecate/ridge/ridge_evaluate_model.py
robyn/_deprecate/ridge/ridge_metrics_calculator.py
robyn/_deprecate/ridge_dec4/ridge_data_builder.py
robyn/_deprecate/ridge_dec4/ridge_evaluate_model.py
robyn/_deprecate/ridge_dec4/ridge_metrics_calculator.py
robyn/_deprecate/ridge_nov30/ridge_data_builder.py
robyn/_deprecate/ridge_nov30/ridge_evaluate_model.py
robyn/_deprecate/ridge_nov30/ridge_metrics_calculator.py
robyn/_deprecate/ridge_nov30_good_v1/ridge_data_builder.py
robyn/_deprecate/ridge_nov30_good_v1/ridge_evaluate_model.py
robyn/_deprecate/ridge_nov30_good_v1/ridge_metrics_calculator.py
robyn/_deprecate/utils/compare_data.py
robyn/_deprecate/utils/data_mapper.py
robyn/_deprecate/utils/plot_utils.py
robyn/allocator/allocator.py
robyn/allocator/constants.py
robyn/allocator/optimizer.py
robyn/allocator/response.py
robyn/allocator/entities/allocation_params.py
robyn/allocator/entities/allocation_result.py
robyn/allocator/entities/constraints.py
robyn/allocator/entities/optimization_result.py
robyn/calibration/media_effect_calibration.py
robyn/calibration/media_transformation.py
robyn/common/common_util.py
robyn/common/constants.py
robyn/common/logger.py
robyn/data/entities/calibration_input.py
robyn/data/entities/enums.py
robynpy-0.3.5.dist-info/licenses/LICENSE
robynpy-0.3.5.dist-info/METADATA
robynpy-0.3.5.dist-info/WHEEL
robynpy-0.3.5.dist-info/top_level.txt
robynpy-0.3.5.dist-info/RECORD
