Metadata-Version: 2.4
Name: robynpy
Version: 0.3.5
Summary: Robyn: Continuous & Semi-Automated MMM. The Open Source Marketing Mix Model Package from Meta Marketing Science
Author-email: Gufeng Zhou <gufeng@meta.com>, Igor Skokan <igorskokan@meta.com>
Project-URL: Homepage, https://github.com/facebookexperimental/Robyn
Project-URL: Issues, https://github.com/facebookexperimental/Robyn/issues
Classifier: Programming Language :: Python :: 3
Classifier: License :: OSI Approved :: MIT License
Classifier: Operating System :: OS Independent
Requires-Python: >=3.8
License-File: LICENSE
Requires-Dist: pandas
Requires-Dist: numpy>=1.20.0
Requires-Dist: matplotlib
Requires-Dist: scikit-learn
Requires-Dist: prophet
Requires-Dist: scipy
Requires-Dist: lmfit
Requires-Dist: plotnine
Requires-Dist: nevergrad
Requires-Dist: seaborn
Requires-Dist: tqdm
Requires-Dist: pytest
Requires-Dist: plotly
Requires-Dist: ipykernel
Requires-Dist: rpy2==3.5.16
Requires-Dist: kaleido==0.2.1
Requires-Dist: nlopt==2.9.1
Requires-Dist: nbformat==5.10.4
Dynamic: license-file
